SqrtRange/__init__.py
SqrtRange/calculator.py
SqrtRange-0.0.7.dist-info/LICENSE
SqrtRange-0.0.7.dist-info/METADATA
SqrtRange-0.0.7.dist-info/WHEEL
SqrtRange-0.0.7.dist-info/top_level.txt
SqrtRange-0.0.7.dist-info/RECORD
