Metadata-Version: 2.1
Name: SqrtRange
Version: 0.0.7
Summary: SqrtRange is a python library used to generate Square root numbers in a range
Home-page: https://github.com/Ricca665/SqrtRange
Author: Ricca665
License: MIT
Classifier: Programming Language :: Python :: 3
Classifier: License :: OSI Approved :: MIT License
Classifier: Operating System :: OS Independent
Requires-Python: >=3.12
License-File: LICENSE
